circuitsim/__init__.py
circuitsim/codegen.py
circuitsim/simulation.py
circuitsim/simulators.py
circuitsim-0.0.1.dist-info/LICENSE
circuitsim-0.0.1.dist-info/METADATA
circuitsim-0.0.1.dist-info/WHEEL
circuitsim-0.0.1.dist-info/top_level.txt
circuitsim-0.0.1.dist-info/RECORD
