Metadata-Version: 2.1
Name: circuitsim
Version: 0.0.1
Summary: Run gate-level HDL simulations from python.
Home-page: https://github.com/circuitgraph/circuitsim
Author: Ruben Purdy
Author-email: rpurdy@andrew.cmu.edu
License: UNKNOWN
Project-URL: Documentation, https://circuitgraph.github.io/circuitsim/
Project-URL: Source, https://github.com/circuitgraph/circuitsim
Platform: UNKNOWN
Classifier: Programming Language :: Python :: 3
Classifier: License :: OSI Approved :: MIT License
Classifier: Operating System :: OS Independent
Requires-Python: >=3.6
License-File: LICENSE
Requires-Dist: circuitgraph (>=0.2.0)
Requires-Dist: natsort
